{
  "metadata": {
    "mayaSceneFile": "C:/Users/mercu/Dropbox/maya/projects/SeedQuest/scenes/NonnaRestaurant/Anim/NPC_Base/NPC_Base_SitChairTable.0001.ma", 
    "angularUnit": "deg", 
    "description": "", 
    "endFrame": 60, 
    "linearUnit": "m", 
    "version": "1.0.0", 
    "references": [
      {
        "node": "NPC_RigRN", 
        "unresolved": "C:/Users/mercu/Dropbox/maya/projects/SeedQuest/scenes/05_NPC/NPC_Base/NPC_Rig.ma", 
        "namespace": ":NPC_Rig", 
        "filename": "C:/Users/mercu/Dropbox/maya/projects/SeedQuest/scenes/05_NPC/NPC_Base/NPC_Rig.ma"
      }
    ], 
    "user": "mercu", 
    "startFrame": 1, 
    "timeUnit": "ntsc", 
    "mayaVersion": "2019", 
    "ctime": "1569465899"
  }
,
  "objects": {
    "NPC_Rig:R_FK_Toe_Ctrl_01": {
      "attrs": {
        "rotateX": {
          "curve": "CURVE1", 
          "type": "doubleAngle", 
          "value": 0.0
        }, 
        "rotateY": {
          "curve": "CURVE2", 
          "type": "doubleAngle", 
          "value": 0.0
        }, 
        "rotateZ": {
          "curve": "CURVE3", 
          "type": "doubleAngle", 
          "value": 0.0
        }
      }
    }, 
    "NPC_Rig:R_Eye_Upper_Ctrl_01": {
      "attrs": {
        "translateX": {
          "curve": "CURVE5", 
          "type": "doubleLinear", 
          "value": 0.0
        }, 
        "translateY": {
          "curve": "CURVE6", 
          "type": "doubleLinear", 
          "value": 0.0
        }, 
        "translateZ": {
          "curve": "CURVE7", 
          "type": "doubleLinear", 
          "value": 0.0
        }, 
        "scaleX": {
          "curve": "CURVE8", 
          "type": "double", 
          "value": 1.0
        }, 
        "scaleY": {
          "curve": "CURVE9", 
          "type": "double", 
          "value": 1.0
        }, 
        "visibility": {
          "curve": "CURVE10", 
          "type": "bool", 
          "value": true
        }, 
        "rotateX": {
          "curve": "CURVE11", 
          "type": "doubleAngle", 
          "value": 0.0
        }, 
        "rotateY": {
          "curve": "CURVE12", 
          "type": "doubleAngle", 
          "value": 0.0
        }, 
        "rotateZ": {
          "curve": "CURVE13", 
          "type": "doubleAngle", 
          "value": 0.0
        }, 
        "scaleZ": {
          "curve": "CURVE14", 
          "type": "double", 
          "value": 1.0
        }
      }
    }, 
    "NPC_Rig:L_FK_Ankle_Ctrl_01": {
      "attrs": {
        "rotateX": {
          "curve": "CURVE16", 
          "type": "doubleAngle", 
          "value": 0.0
        }, 
        "rotateY": {
          "curve": "CURVE17", 
          "type": "doubleAngle", 
          "value": 0.0
        }, 
        "rotateZ": {
          "curve": "CURVE18", 
          "type": "doubleAngle", 
          "value": 0.0
        }
      }
    }, 
    "NPC_Rig:Head_Ctrl_01": {
      "attrs": {
        "translateX": {
          "curve": "CURVE20", 
          "type": "doubleLinear", 
          "value": 0.0
        }, 
        "translateY": {
          "curve": "CURVE21", 
          "type": "doubleLinear", 
          "value": 0.0
        }, 
        "translateZ": {
          "curve": "CURVE22", 
          "type": "doubleLinear", 
          "value": 0.0
        }, 
        "scaleX": {
          "curve": "CURVE23", 
          "type": "double", 
          "value": 1.0
        }, 
        "scaleY": {
          "curve": "CURVE24", 
          "type": "double", 
          "value": 1.0
        }, 
        "visibility": {
          "curve": "CURVE25", 
          "type": "bool", 
          "value": true
        }, 
        "rotateX": {
          "curve": "CURVE26", 
          "type": "doubleAngle", 
          "value": 0.0
        }, 
        "rotateY": {
          "curve": "CURVE27", 
          "type": "doubleAngle", 
          "value": 0.0
        }, 
        "rotateZ": {
          "curve": "CURVE28", 
          "type": "doubleAngle", 
          "value": 0.0
        }, 
        "scaleZ": {
          "curve": "CURVE29", 
          "type": "double", 
          "value": 1.0
        }
      }
    }, 
    "NPC_Rig:R_FK_Knee_Ctrl_01": {
      "attrs": {
        "rotateX": {
          "curve": "CURVE31", 
          "type": "doubleAngle", 
          "value": 0.0
        }, 
        "rotateY": {
          "curve": "CURVE32", 
          "type": "doubleAngle", 
          "value": 0.0
        }, 
        "rotateZ": {
          "curve": "CURVE33", 
          "type": "doubleAngle", 
          "value": 0.0
        }
      }
    }, 
    "NPC_Rig:R_FK_Leg_Ctrl_01": {
      "attrs": {
        "rotateX": {
          "curve": "CURVE35", 
          "type": "doubleAngle", 
          "value": -19.150373349414703
        }, 
        "rotateY": {
          "curve": "CURVE36", 
          "type": "doubleAngle", 
          "value": 7.698807428360229
        }, 
        "rotateZ": {
          "curve": "CURVE37", 
          "type": "doubleAngle", 
          "value": 83.78739764098428
        }
      }
    }, 
    "NPC_Rig:L_Index_Ctrl_02": {
      "attrs": {
        "rotateX": {
          "curve": "CURVE39", 
          "type": "doubleAngle", 
          "value": -0.33171204254501035
        }, 
        "rotateY": {
          "curve": "CURVE40", 
          "type": "doubleAngle", 
          "value": 0.035225743496003124
        }, 
        "rotateZ": {
          "curve": "CURVE41", 
          "type": "doubleAngle", 
          "value": -9.358184717696018
        }
      }
    }, 
    "NPC_Rig:L_FK_Leg_Ctrl_01": {
      "attrs": {
        "rotateX": {
          "curve": "CURVE43", 
          "type": "doubleAngle", 
          "value": -13.182306548638504
        }, 
        "rotateY": {
          "curve": "CURVE44", 
          "type": "doubleAngle", 
          "value": 15.134505802532113
        }, 
        "rotateZ": {
          "curve": "CURVE45", 
          "type": "doubleAngle", 
          "value": 83.81674783089446
        }
      }
    }, 
    "NPC_Rig:R_Thumb_Ctrl_03": {
      "attrs": {
        "rotateX": {
          "curve": "CURVE47", 
          "type": "doubleAngle", 
          "value": 0.0
        }, 
        "rotateY": {
          "curve": "CURVE48", 
          "type": "doubleAngle", 
          "value": 0.0
        }, 
        "rotateZ": {
          "curve": "CURVE49", 
          "type": "doubleAngle", 
          "value": -3.1292236585888005
        }
      }
    }, 
    "NPC_Rig:R_Thumb_Ctrl_02": {
      "attrs": {
        "rotateX": {
          "curve": "CURVE51", 
          "type": "doubleAngle", 
          "value": 0.0
        }, 
        "rotateY": {
          "curve": "CURVE52", 
          "type": "doubleAngle", 
          "value": 0.0
        }, 
        "rotateZ": {
          "curve": "CURVE53", 
          "type": "doubleAngle", 
          "value": -10.232157964801976
        }
      }
    }, 
    "NPC_Rig:R_Thumb_Ctrl_01": {
      "attrs": {
        "rotateX": {
          "curve": "CURVE55", 
          "type": "doubleAngle", 
          "value": 4.135026911479591e-16
        }, 
        "rotateY": {
          "curve": "CURVE56", 
          "type": "doubleAngle", 
          "value": 15.95719639264725
        }, 
        "rotateZ": {
          "curve": "CURVE57", 
          "type": "doubleAngle", 
          "value": -9.129062742897872
        }
      }
    }, 
    "NPC_Rig:L_Pinky_Ctrl_01": {
      "attrs": {
        "rotateX": {
          "curve": "CURVE59", 
          "type": "doubleAngle", 
          "value": 0.0
        }, 
        "rotateY": {
          "curve": "CURVE60", 
          "type": "doubleAngle", 
          "value": 0.0
        }, 
        "rotateZ": {
          "curve": "CURVE61", 
          "type": "doubleAngle", 
          "value": 0.0
        }
      }
    }, 
    "NPC_Rig:L_FK_Foot_Ctrl_01": {
      "attrs": {
        "rotateX": {
          "curve": "CURVE63", 
          "type": "doubleAngle", 
          "value": 0.0
        }, 
        "rotateY": {
          "curve": "CURVE64", 
          "type": "doubleAngle", 
          "value": 0.0
        }, 
        "rotateZ": {
          "curve": "CURVE65", 
          "type": "doubleAngle", 
          "value": 0.0
        }
      }
    }, 
    "NPC_Rig:L_Pinky_Ctrl_03": {
      "attrs": {
        "rotateX": {
          "curve": "CURVE67", 
          "type": "doubleAngle", 
          "value": 0.0
        }, 
        "rotateY": {
          "curve": "CURVE68", 
          "type": "doubleAngle", 
          "value": 0.0
        }, 
        "rotateZ": {
          "curve": "CURVE69", 
          "type": "doubleAngle", 
          "value": -11.85170543209327
        }
      }
    }, 
    "NPC_Rig:R_FK_Foot_Ctrl_01": {
      "attrs": {
        "rotateX": {
          "curve": "CURVE71", 
          "type": "doubleAngle", 
          "value": 0.0
        }, 
        "rotateY": {
          "curve": "CURVE72", 
          "type": "doubleAngle", 
          "value": 0.0
        }, 
        "rotateZ": {
          "curve": "CURVE73", 
          "type": "doubleAngle", 
          "value": 0.0
        }
      }
    }, 
    "NPC_Rig:L_Pinky_Ctrl_02": {
      "attrs": {
        "rotateX": {
          "curve": "CURVE75", 
          "type": "doubleAngle", 
          "value": 0.0
        }, 
        "rotateY": {
          "curve": "CURVE76", 
          "type": "doubleAngle", 
          "value": 0.0
        }, 
        "rotateZ": {
          "curve": "CURVE77", 
          "type": "doubleAngle", 
          "value": -11.85170543209327
        }
      }
    }, 
    "NPC_Rig:L_Foot_IKFK": {
      "attrs": {
        "IK_FK_Switch": {
          "curve": "CURVE79", 
          "type": "double", 
          "value": 0.0
        }
      }
    }, 
    "NPC_Rig:R_Eye_Lower_Ctrl_01": {
      "attrs": {
        "translateX": {
          "curve": "CURVE81", 
          "type": "doubleLinear", 
          "value": 0.0
        }, 
        "translateY": {
          "curve": "CURVE82", 
          "type": "doubleLinear", 
          "value": 0.0
        }, 
        "translateZ": {
          "curve": "CURVE83", 
          "type": "doubleLinear", 
          "value": 0.0
        }, 
        "scaleX": {
          "curve": "CURVE84", 
          "type": "double", 
          "value": 1.0
        }, 
        "scaleY": {
          "curve": "CURVE85", 
          "type": "double", 
          "value": 1.0
        }, 
        "visibility": {
          "curve": "CURVE86", 
          "type": "bool", 
          "value": true
        }, 
        "rotateX": {
          "curve": "CURVE87", 
          "type": "doubleAngle", 
          "value": 0.0
        }, 
        "rotateY": {
          "curve": "CURVE88", 
          "type": "doubleAngle", 
          "value": 0.0
        }, 
        "rotateZ": {
          "curve": "CURVE89", 
          "type": "doubleAngle", 
          "value": 0.0
        }, 
        "scaleZ": {
          "curve": "CURVE90", 
          "type": "double", 
          "value": 1.0
        }
      }
    }, 
    "NPC_Rig:R_Pinky_Ctrl_02": {
      "attrs": {
        "rotateX": {
          "curve": "CURVE92", 
          "type": "doubleAngle", 
          "value": 0.0
        }, 
        "rotateY": {
          "curve": "CURVE93", 
          "type": "doubleAngle", 
          "value": 0.0
        }, 
        "rotateZ": {
          "curve": "CURVE94", 
          "type": "doubleAngle", 
          "value": -11.85170543209327
        }
      }
    }, 
    "NPC_Rig:R_Pinky_Ctrl_03": {
      "attrs": {
        "rotateX": {
          "curve": "CURVE96", 
          "type": "doubleAngle", 
          "value": 0.0
        }, 
        "rotateY": {
          "curve": "CURVE97", 
          "type": "doubleAngle", 
          "value": 0.0
        }, 
        "rotateZ": {
          "curve": "CURVE98", 
          "type": "doubleAngle", 
          "value": -11.85170543209327
        }
      }
    }, 
    "NPC_Rig:R_Pinky_Ctrl_01": {
      "attrs": {
        "rotateX": {
          "curve": "CURVE100", 
          "type": "doubleAngle", 
          "value": 0.0
        }, 
        "rotateY": {
          "curve": "CURVE101", 
          "type": "doubleAngle", 
          "value": 0.0
        }, 
        "rotateZ": {
          "curve": "CURVE102", 
          "type": "doubleAngle", 
          "value": 0.0
        }
      }
    }, 
    "NPC_Rig:L_Middle_Ctrl_03": {
      "attrs": {
        "rotateX": {
          "curve": "CURVE104", 
          "type": "doubleAngle", 
          "value": 0.0
        }, 
        "rotateY": {
          "curve": "CURVE105", 
          "type": "doubleAngle", 
          "value": 0.0
        }, 
        "rotateZ": {
          "curve": "CURVE106", 
          "type": "doubleAngle", 
          "value": -11.85170543209327
        }
      }
    }, 
    "NPC_Rig:L_Middle_Ctrl_02": {
      "attrs": {
        "rotateX": {
          "curve": "CURVE108", 
          "type": "doubleAngle", 
          "value": 0.0
        }, 
        "rotateY": {
          "curve": "CURVE109", 
          "type": "doubleAngle", 
          "value": 0.0
        }, 
        "rotateZ": {
          "curve": "CURVE110", 
          "type": "doubleAngle", 
          "value": -11.85170543209327
        }
      }
    }, 
    "NPC_Rig:L_Middle_Ctrl_01": {
      "attrs": {
        "rotateX": {
          "curve": "CURVE112", 
          "type": "doubleAngle", 
          "value": 0.0
        }, 
        "rotateY": {
          "curve": "CURVE113", 
          "type": "doubleAngle", 
          "value": 0.0
        }, 
        "rotateZ": {
          "curve": "CURVE114", 
          "type": "doubleAngle", 
          "value": 0.0
        }
      }
    }, 
    "NPC_Rig:L_FK_Knee_Ctrl_01": {
      "attrs": {
        "rotateX": {
          "curve": "CURVE116", 
          "type": "doubleAngle", 
          "value": 0.0
        }, 
        "rotateY": {
          "curve": "CURVE117", 
          "type": "doubleAngle", 
          "value": 0.0
        }, 
        "rotateZ": {
          "curve": "CURVE118", 
          "type": "doubleAngle", 
          "value": 0.0
        }
      }
    }, 
    "NPC_Rig:R_Middle_Ctrl_03": {
      "attrs": {
        "rotateX": {
          "curve": "CURVE120", 
          "type": "doubleAngle", 
          "value": 0.0
        }, 
        "rotateY": {
          "curve": "CURVE121", 
          "type": "doubleAngle", 
          "value": 0.0
        }, 
        "rotateZ": {
          "curve": "CURVE122", 
          "type": "doubleAngle", 
          "value": -11.85170543209327
        }
      }
    }, 
    "NPC_Rig:L_Eye_Lower_Ctrl_01": {
      "attrs": {
        "translateX": {
          "curve": "CURVE124", 
          "type": "doubleLinear", 
          "value": 0.0
        }, 
        "translateY": {
          "curve": "CURVE125", 
          "type": "doubleLinear", 
          "value": 0.0
        }, 
        "translateZ": {
          "curve": "CURVE126", 
          "type": "doubleLinear", 
          "value": 0.0
        }, 
        "scaleX": {
          "curve": "CURVE127", 
          "type": "double", 
          "value": 1.0
        }, 
        "scaleY": {
          "curve": "CURVE128", 
          "type": "double", 
          "value": 1.0
        }, 
        "visibility": {
          "curve": "CURVE129", 
          "type": "bool", 
          "value": true
        }, 
        "rotateX": {
          "curve": "CURVE130", 
          "type": "doubleAngle", 
          "value": 0.0
        }, 
        "rotateY": {
          "curve": "CURVE131", 
          "type": "doubleAngle", 
          "value": 0.0
        }, 
        "rotateZ": {
          "curve": "CURVE132", 
          "type": "doubleAngle", 
          "value": 0.0
        }, 
        "scaleZ": {
          "curve": "CURVE133", 
          "type": "double", 
          "value": 1.0
        }
      }
    }, 
    "NPC_Rig:R_Middle_Ctrl_01": {
      "attrs": {
        "rotateX": {
          "curve": "CURVE135", 
          "type": "doubleAngle", 
          "value": 0.0
        }, 
        "rotateY": {
          "curve": "CURVE136", 
          "type": "doubleAngle", 
          "value": 0.0
        }, 
        "rotateZ": {
          "curve": "CURVE137", 
          "type": "doubleAngle", 
          "value": 0.0
        }
      }
    }, 
    "NPC_Rig:R_Eyebrow_Inner_Ctrl_01": {
      "attrs": {
        "translateX": {
          "curve": "CURVE139", 
          "type": "doubleLinear", 
          "value": 0.0
        }, 
        "translateY": {
          "curve": "CURVE140", 
          "type": "doubleLinear", 
          "value": 0.0
        }, 
        "translateZ": {
          "curve": "CURVE141", 
          "type": "doubleLinear", 
          "value": 0.0
        }, 
        "scaleX": {
          "curve": "CURVE142", 
          "type": "double", 
          "value": 1.0
        }, 
        "scaleY": {
          "curve": "CURVE143", 
          "type": "double", 
          "value": 1.0
        }, 
        "visibility": {
          "curve": "CURVE144", 
          "type": "bool", 
          "value": true
        }, 
        "rotateX": {
          "curve": "CURVE145", 
          "type": "doubleAngle", 
          "value": 0.0
        }, 
        "rotateY": {
          "curve": "CURVE146", 
          "type": "doubleAngle", 
          "value": 0.0
        }, 
        "rotateZ": {
          "curve": "CURVE147", 
          "type": "doubleAngle", 
          "value": 0.0
        }, 
        "scaleZ": {
          "curve": "CURVE148", 
          "type": "double", 
          "value": 1.0
        }
      }
    }, 
    "NPC_Rig:R_Middle_Ctrl_02": {
      "attrs": {
        "rotateX": {
          "curve": "CURVE150", 
          "type": "doubleAngle", 
          "value": 0.0
        }, 
        "rotateY": {
          "curve": "CURVE151", 
          "type": "doubleAngle", 
          "value": 0.0
        }, 
        "rotateZ": {
          "curve": "CURVE152", 
          "type": "doubleAngle", 
          "value": -11.85170543209327
        }
      }
    }, 
    "NPC_Rig:R_FK_Ankle_Ctrl_01": {
      "attrs": {
        "rotateX": {
          "curve": "CURVE154", 
          "type": "doubleAngle", 
          "value": 0.0
        }, 
        "rotateY": {
          "curve": "CURVE155", 
          "type": "doubleAngle", 
          "value": 0.0
        }, 
        "rotateZ": {
          "curve": "CURVE156", 
          "type": "doubleAngle", 
          "value": 0.0
        }
      }
    }, 
    "NPC_Rig:Master_NPC_Ctrl_01": {
      "attrs": {
        "translateX": {
          "curve": "CURVE158", 
          "type": "doubleLinear", 
          "value": 0.0
        }, 
        "translateY": {
          "curve": "CURVE159", 
          "type": "doubleLinear", 
          "value": 0.0
        }, 
        "translateZ": {
          "curve": "CURVE160", 
          "type": "doubleLinear", 
          "value": 0.0
        }, 
        "scaleX": {
          "curve": "CURVE161", 
          "type": "double", 
          "value": 1.0
        }, 
        "scaleY": {
          "curve": "CURVE162", 
          "type": "double", 
          "value": 1.0
        }, 
        "visibility": {
          "curve": "CURVE163", 
          "type": "bool", 
          "value": true
        }, 
        "rotateX": {
          "curve": "CURVE164", 
          "type": "doubleAngle", 
          "value": 0.0
        }, 
        "rotateY": {
          "curve": "CURVE165", 
          "type": "doubleAngle", 
          "value": 0.0
        }, 
        "rotateZ": {
          "curve": "CURVE166", 
          "type": "doubleAngle", 
          "value": 0.0
        }, 
        "scaleZ": {
          "curve": "CURVE167", 
          "type": "double", 
          "value": 1.0
        }
      }
    }, 
    "NPC_Rig:L_FK_Toe_Ctrl_01": {
      "attrs": {
        "rotateX": {
          "curve": "CURVE169", 
          "type": "doubleAngle", 
          "value": 0.0
        }, 
        "rotateY": {
          "curve": "CURVE170", 
          "type": "doubleAngle", 
          "value": 0.0
        }, 
        "rotateZ": {
          "curve": "CURVE171", 
          "type": "doubleAngle", 
          "value": 0.0
        }
      }
    }, 
    "NPC_Rig:L_Eye_Upper_Ctrl_01": {
      "attrs": {
        "translateX": {
          "curve": "CURVE173", 
          "type": "doubleLinear", 
          "value": 0.0
        }, 
        "translateY": {
          "curve": "CURVE174", 
          "type": "doubleLinear", 
          "value": 0.0
        }, 
        "translateZ": {
          "curve": "CURVE175", 
          "type": "doubleLinear", 
          "value": 0.0
        }, 
        "scaleX": {
          "curve": "CURVE176", 
          "type": "double", 
          "value": 1.0
        }, 
        "scaleY": {
          "curve": "CURVE177", 
          "type": "double", 
          "value": 1.0
        }, 
        "visibility": {
          "curve": "CURVE178", 
          "type": "bool", 
          "value": true
        }, 
        "rotateX": {
          "curve": "CURVE179", 
          "type": "doubleAngle", 
          "value": 0.0
        }, 
        "rotateY": {
          "curve": "CURVE180", 
          "type": "doubleAngle", 
          "value": 0.0
        }, 
        "rotateZ": {
          "curve": "CURVE181", 
          "type": "doubleAngle", 
          "value": 0.0
        }, 
        "scaleZ": {
          "curve": "CURVE182", 
          "type": "double", 
          "value": 1.0
        }
      }
    }, 
    "NPC_Rig:L_Eye_Ctrl_01": {
      "attrs": {
        "translateX": {
          "curve": "CURVE184", 
          "type": "doubleLinear", 
          "value": 0.0
        }, 
        "translateY": {
          "curve": "CURVE185", 
          "type": "doubleLinear", 
          "value": 0.0
        }, 
        "translateZ": {
          "curve": "CURVE186", 
          "type": "doubleLinear", 
          "value": 0.0
        }, 
        "scaleX": {
          "curve": "CURVE187", 
          "type": "double", 
          "value": 1.0
        }, 
        "scaleY": {
          "curve": "CURVE188", 
          "type": "double", 
          "value": 1.0
        }, 
        "visibility": {
          "curve": "CURVE189", 
          "type": "bool", 
          "value": true
        }, 
        "rotateX": {
          "curve": "CURVE190", 
          "type": "doubleAngle", 
          "value": 0.0
        }, 
        "rotateY": {
          "curve": "CURVE191", 
          "type": "doubleAngle", 
          "value": 0.0
        }, 
        "rotateZ": {
          "curve": "CURVE192", 
          "type": "doubleAngle", 
          "value": 0.0
        }, 
        "scaleZ": {
          "curve": "CURVE193", 
          "type": "double", 
          "value": 1.0
        }
      }
    }, 
    "NPC_Rig:L_Thumb_Ctrl_01": {
      "attrs": {
        "rotateX": {
          "curve": "CURVE195", 
          "type": "doubleAngle", 
          "value": 4.135026911479591e-16
        }, 
        "rotateY": {
          "curve": "CURVE196", 
          "type": "doubleAngle", 
          "value": 15.95719639264725
        }, 
        "rotateZ": {
          "curve": "CURVE197", 
          "type": "doubleAngle", 
          "value": -9.129062742897872
        }
      }
    }, 
    "NPC_Rig:Spine_Ctrl_01": {
      "attrs": {
        "translateX": {
          "curve": "CURVE199", 
          "type": "doubleLinear", 
          "value": 0.0
        }, 
        "translateY": {
          "curve": "CURVE200", 
          "type": "doubleLinear", 
          "value": 0.0
        }, 
        "translateZ": {
          "curve": "CURVE201", 
          "type": "doubleLinear", 
          "value": 0.0
        }, 
        "rotateY": {
          "curve": "CURVE202", 
          "type": "doubleAngle", 
          "value": -0.0
        }, 
        "rotateX": {
          "curve": "CURVE203", 
          "type": "doubleAngle", 
          "value": -0.0
        }, 
        "Stretch_Multiplier": {
          "curve": "CURVE204", 
          "type": "double", 
          "value": 1.0
        }, 
        "rotateZ": {
          "curve": "CURVE205", 
          "type": "doubleAngle", 
          "value": 0.0
        }
      }
    }, 
    "NPC_Rig:L_Thumb_Ctrl_03": {
      "attrs": {
        "rotateX": {
          "curve": "CURVE207", 
          "type": "doubleAngle", 
          "value": 0.0
        }, 
        "rotateY": {
          "curve": "CURVE208", 
          "type": "doubleAngle", 
          "value": 0.0
        }, 
        "rotateZ": {
          "curve": "CURVE209", 
          "type": "doubleAngle", 
          "value": -3.1292236585888005
        }
      }
    }, 
    "NPC_Rig:L_Thumb_Ctrl_02": {
      "attrs": {
        "rotateX": {
          "curve": "CURVE211", 
          "type": "doubleAngle", 
          "value": 0.0
        }, 
        "rotateY": {
          "curve": "CURVE212", 
          "type": "doubleAngle", 
          "value": 0.0
        }, 
        "rotateZ": {
          "curve": "CURVE213", 
          "type": "doubleAngle", 
          "value": -10.232157964801976
        }
      }
    }, 
    "NPC_Rig:L_Lip_Ctrl_01": {
      "attrs": {
        "translateX": {
          "curve": "CURVE215", 
          "type": "doubleLinear", 
          "value": 0.011098472204925816
        }, 
        "translateY": {
          "curve": "CURVE216", 
          "type": "doubleLinear", 
          "value": 0.010711343175781561
        }, 
        "translateZ": {
          "curve": "CURVE217", 
          "type": "doubleLinear", 
          "value": -0.03185738297297323
        }, 
        "scaleX": {
          "curve": "CURVE218", 
          "type": "double", 
          "value": 1.0
        }, 
        "scaleY": {
          "curve": "CURVE219", 
          "type": "double", 
          "value": 1.0
        }, 
        "visibility": {
          "curve": "CURVE220", 
          "type": "bool", 
          "value": true
        }, 
        "rotateX": {
          "curve": "CURVE221", 
          "type": "doubleAngle", 
          "value": 0.0
        }, 
        "rotateY": {
          "curve": "CURVE222", 
          "type": "doubleAngle", 
          "value": 0.0
        }, 
        "rotateZ": {
          "curve": "CURVE223", 
          "type": "doubleAngle", 
          "value": 0.0
        }, 
        "scaleZ": {
          "curve": "CURVE224", 
          "type": "double", 
          "value": 1.0
        }
      }
    }, 
    "NPC_Rig:L_Index_Ctrl_01": {
      "attrs": {
        "rotateX": {
          "curve": "CURVE226", 
          "type": "doubleAngle", 
          "value": 0.0
        }, 
        "rotateY": {
          "curve": "CURVE227", 
          "type": "doubleAngle", 
          "value": 0.0
        }, 
        "rotateZ": {
          "curve": "CURVE228", 
          "type": "doubleAngle", 
          "value": -9.901586302668461
        }
      }
    }, 
    "NPC_Rig:R_Foot_IKFK": {
      "attrs": {
        "IK_FK_Switch": {
          "curve": "CURVE230", 
          "type": "double", 
          "value": 0.0
        }
      }
    }, 
    "NPC_Rig:R_FK_Wrist_Ctrl_01": {
      "attrs": {
        "rotateX": {
          "curve": "CURVE232", 
          "type": "doubleAngle", 
          "value": 30.56669781405711
        }, 
        "rotateY": {
          "curve": "CURVE233", 
          "type": "doubleAngle", 
          "value": 0.0
        }, 
        "rotateZ": {
          "curve": "CURVE234", 
          "type": "doubleAngle", 
          "value": 0.0
        }
      }
    }, 
    "NPC_Rig:L_Hand_IKFK": {
      "attrs": {
        "IK_FK_Switch": {
          "curve": "CURVE236", 
          "type": "double", 
          "value": 0.0
        }
      }
    }, 
    "NPC_Rig:Jaw_Ctrl_01": {
      "attrs": {
        "translateX": {
          "curve": "CURVE238", 
          "type": "doubleLinear", 
          "value": 0.0
        }, 
        "translateY": {
          "curve": "CURVE239", 
          "type": "doubleLinear", 
          "value": 0.0
        }, 
        "translateZ": {
          "curve": "CURVE240", 
          "type": "doubleLinear", 
          "value": 0.0
        }, 
        "rotateX": {
          "curve": "CURVE241", 
          "type": "doubleAngle", 
          "value": 0.0
        }, 
        "rotateY": {
          "curve": "CURVE242", 
          "type": "doubleAngle", 
          "value": 0.0
        }, 
        "rotateZ": {
          "curve": "CURVE243", 
          "type": "doubleAngle", 
          "value": -6.207594123023576
        }
      }
    }, 
    "NPC_Rig:L_Eyebrow_Outer_Ctrl_01": {
      "attrs": {
        "translateX": {
          "curve": "CURVE245", 
          "type": "doubleLinear", 
          "value": 0.0
        }, 
        "translateY": {
          "curve": "CURVE246", 
          "type": "doubleLinear", 
          "value": 0.0
        }, 
        "translateZ": {
          "curve": "CURVE247", 
          "type": "doubleLinear", 
          "value": 0.0
        }, 
        "scaleX": {
          "curve": "CURVE248", 
          "type": "double", 
          "value": 1.0
        }, 
        "scaleY": {
          "curve": "CURVE249", 
          "type": "double", 
          "value": 1.0
        }, 
        "visibility": {
          "curve": "CURVE250", 
          "type": "bool", 
          "value": true
        }, 
        "rotateX": {
          "curve": "CURVE251", 
          "type": "doubleAngle", 
          "value": 0.0
        }, 
        "rotateY": {
          "curve": "CURVE252", 
          "type": "doubleAngle", 
          "value": 0.0
        }, 
        "rotateZ": {
          "curve": "CURVE253", 
          "type": "doubleAngle", 
          "value": 0.0
        }, 
        "scaleZ": {
          "curve": "CURVE254", 
          "type": "double", 
          "value": 1.0
        }
      }
    }, 
    "NPC_Rig:R_FK_Clavical_Ctrl_01": {
      "attrs": {
        "rotateX": {
          "curve": "CURVE256", 
          "type": "doubleAngle", 
          "value": 0.0
        }, 
        "rotateY": {
          "curve": "CURVE257", 
          "type": "doubleAngle", 
          "value": 0.0
        }, 
        "rotateZ": {
          "curve": "CURVE258", 
          "type": "doubleAngle", 
          "value": 0.0
        }
      }
    }, 
    "NPC_Rig:Chest_Ctrl_01": {
      "attrs": {
        "translateX": {
          "curve": "CURVE260", 
          "type": "doubleLinear", 
          "value": 0.0
        }, 
        "translateY": {
          "curve": "CURVE261", 
          "type": "doubleLinear", 
          "value": 0.0
        }, 
        "translateZ": {
          "curve": "CURVE262", 
          "type": "doubleLinear", 
          "value": -0.0
        }, 
        "scaleX": {
          "curve": "CURVE263", 
          "type": "double", 
          "value": 1.0
        }, 
        "scaleY": {
          "curve": "CURVE264", 
          "type": "double", 
          "value": 1.0
        }, 
        "visibility": {
          "curve": "CURVE265", 
          "type": "bool", 
          "value": true
        }, 
        "rotateX": {
          "curve": "CURVE266", 
          "type": "doubleAngle", 
          "value": -0.0
        }, 
        "rotateY": {
          "curve": "CURVE267", 
          "type": "doubleAngle", 
          "value": -0.0
        }, 
        "rotateZ": {
          "curve": "CURVE268", 
          "type": "doubleAngle", 
          "value": 0.0
        }, 
        "scaleZ": {
          "curve": "CURVE269", 
          "type": "double", 
          "value": 1.0
        }
      }
    }, 
    "NPC_Rig:Upper_Lip_Ctrl_01": {
      "attrs": {
        "translateX": {
          "curve": "CURVE271", 
          "type": "doubleLinear", 
          "value": 0.0
        }, 
        "translateY": {
          "curve": "CURVE272", 
          "type": "doubleLinear", 
          "value": 0.0
        }, 
        "translateZ": {
          "curve": "CURVE273", 
          "type": "doubleLinear", 
          "value": 0.0
        }, 
        "scaleX": {
          "curve": "CURVE274", 
          "type": "double", 
          "value": 1.0
        }, 
        "scaleY": {
          "curve": "CURVE275", 
          "type": "double", 
          "value": 1.0
        }, 
        "visibility": {
          "curve": "CURVE276", 
          "type": "bool", 
          "value": true
        }, 
        "rotateX": {
          "curve": "CURVE277", 
          "type": "doubleAngle", 
          "value": 0.0
        }, 
        "rotateY": {
          "curve": "CURVE278", 
          "type": "doubleAngle", 
          "value": 0.0
        }, 
        "rotateZ": {
          "curve": "CURVE279", 
          "type": "doubleAngle", 
          "value": 0.0
        }, 
        "scaleZ": {
          "curve": "CURVE280", 
          "type": "double", 
          "value": 1.0
        }
      }
    }, 
    "NPC_Rig:L_FK_Shoulder_Ctrl_01": {
      "attrs": {
        "rotateX": {
          "curve": "CURVE282", 
          "type": "doubleAngle", 
          "value": -19.79507727119568
        }, 
        "rotateY": {
          "curve": "CURVE283", 
          "type": "doubleAngle", 
          "value": -64.73774979921906
        }, 
        "rotateZ": {
          "curve": "CURVE284", 
          "type": "doubleAngle", 
          "value": -29.29970392710971
        }
      }
    }, 
    "NPC_Rig:Waist_Ctrl_01": {
      "attrs": {
        "translateX": {
          "curve": "CURVE286", 
          "type": "doubleLinear", 
          "value": 0.0
        }, 
        "translateY": {
          "curve": "CURVE287", 
          "type": "doubleLinear", 
          "value": 0.16810364790077104
        }, 
        "translateZ": {
          "curve": "CURVE288", 
          "type": "doubleLinear", 
          "value": 0.0
        }, 
        "rotateX": {
          "curve": "CURVE289", 
          "type": "doubleAngle", 
          "value": 0.0
        }, 
        "rotateY": {
          "curve": "CURVE290", 
          "type": "doubleAngle", 
          "value": -0.0
        }, 
        "rotateZ": {
          "curve": "CURVE291", 
          "type": "doubleAngle", 
          "value": 0.0
        }
      }
    }, 
    "NPC_Rig:R_FK_Shoulder_Ctrl_01": {
      "attrs": {
        "rotateX": {
          "curve": "CURVE293", 
          "type": "doubleAngle", 
          "value": -19.79507727119568
        }, 
        "rotateY": {
          "curve": "CURVE294", 
          "type": "doubleAngle", 
          "value": -64.73774979921906
        }, 
        "rotateZ": {
          "curve": "CURVE295", 
          "type": "doubleAngle", 
          "value": -29.29970392710971
        }
      }
    }, 
    "NPC_Rig:L_Eyebrow_Inner_Ctrl_01": {
      "attrs": {
        "translateX": {
          "curve": "CURVE297", 
          "type": "doubleLinear", 
          "value": 0.0
        }, 
        "translateY": {
          "curve": "CURVE298", 
          "type": "doubleLinear", 
          "value": 0.0
        }, 
        "translateZ": {
          "curve": "CURVE299", 
          "type": "doubleLinear", 
          "value": 0.0
        }, 
        "scaleX": {
          "curve": "CURVE300", 
          "type": "double", 
          "value": 1.0
        }, 
        "scaleY": {
          "curve": "CURVE301", 
          "type": "double", 
          "value": 1.0
        }, 
        "visibility": {
          "curve": "CURVE302", 
          "type": "bool", 
          "value": true
        }, 
        "rotateX": {
          "curve": "CURVE303", 
          "type": "doubleAngle", 
          "value": 0.0
        }, 
        "rotateY": {
          "curve": "CURVE304", 
          "type": "doubleAngle", 
          "value": 0.0
        }, 
        "rotateZ": {
          "curve": "CURVE305", 
          "type": "doubleAngle", 
          "value": 0.0
        }, 
        "scaleZ": {
          "curve": "CURVE306", 
          "type": "double", 
          "value": 1.0
        }
      }
    }, 
    "NPC_Rig:R_Eyebrow_Outer_Ctrl_01": {
      "attrs": {
        "translateX": {
          "curve": "CURVE308", 
          "type": "doubleLinear", 
          "value": 0.0
        }, 
        "translateY": {
          "curve": "CURVE309", 
          "type": "doubleLinear", 
          "value": 0.0
        }, 
        "translateZ": {
          "curve": "CURVE310", 
          "type": "doubleLinear", 
          "value": 0.0
        }, 
        "scaleX": {
          "curve": "CURVE311", 
          "type": "double", 
          "value": 1.0
        }, 
        "scaleY": {
          "curve": "CURVE312", 
          "type": "double", 
          "value": 1.0
        }, 
        "visibility": {
          "curve": "CURVE313", 
          "type": "bool", 
          "value": true
        }, 
        "rotateX": {
          "curve": "CURVE314", 
          "type": "doubleAngle", 
          "value": 0.0
        }, 
        "rotateY": {
          "curve": "CURVE315", 
          "type": "doubleAngle", 
          "value": 0.0
        }, 
        "rotateZ": {
          "curve": "CURVE316", 
          "type": "doubleAngle", 
          "value": 0.0
        }, 
        "scaleZ": {
          "curve": "CURVE317", 
          "type": "double", 
          "value": 1.0
        }
      }
    }, 
    "NPC_Rig:R_FK_Elbow_Ctrl_01": {
      "attrs": {
        "rotateX": {
          "curve": "CURVE319", 
          "type": "doubleAngle", 
          "value": 0.0
        }, 
        "rotateY": {
          "curve": "CURVE320", 
          "type": "doubleAngle", 
          "value": 0.0
        }, 
        "rotateZ": {
          "curve": "CURVE321", 
          "type": "doubleAngle", 
          "value": 0.0
        }
      }
    }, 
    "NPC_Rig:Nose_Ctrl_01": {
      "attrs": {
        "translateX": {
          "curve": "CURVE323", 
          "type": "doubleLinear", 
          "value": 0.0
        }, 
        "translateY": {
          "curve": "CURVE324", 
          "type": "doubleLinear", 
          "value": 0.0
        }, 
        "translateZ": {
          "curve": "CURVE325", 
          "type": "doubleLinear", 
          "value": 0.0
        }, 
        "scaleX": {
          "curve": "CURVE326", 
          "type": "double", 
          "value": 1.0
        }, 
        "scaleY": {
          "curve": "CURVE327", 
          "type": "double", 
          "value": 1.0
        }, 
        "visibility": {
          "curve": "CURVE328", 
          "type": "bool", 
          "value": true
        }, 
        "rotateX": {
          "curve": "CURVE329", 
          "type": "doubleAngle", 
          "value": 0.0
        }, 
        "rotateY": {
          "curve": "CURVE330", 
          "type": "doubleAngle", 
          "value": 0.0
        }, 
        "rotateZ": {
          "curve": "CURVE331", 
          "type": "doubleAngle", 
          "value": 0.0
        }, 
        "scaleZ": {
          "curve": "CURVE332", 
          "type": "double", 
          "value": 1.0
        }
      }
    }, 
    "NPC_Rig:R_Index_Ctrl_03": {
      "attrs": {
        "rotateX": {
          "curve": "CURVE334", 
          "type": "doubleAngle", 
          "value": 0.0
        }, 
        "rotateY": {
          "curve": "CURVE335", 
          "type": "doubleAngle", 
          "value": 0.0
        }, 
        "rotateZ": {
          "curve": "CURVE336", 
          "type": "doubleAngle", 
          "value": 0.0
        }
      }
    }, 
    "NPC_Rig:R_Index_Ctrl_02": {
      "attrs": {
        "rotateX": {
          "curve": "CURVE338", 
          "type": "doubleAngle", 
          "value": -0.33171204254501035
        }, 
        "rotateY": {
          "curve": "CURVE339", 
          "type": "doubleAngle", 
          "value": 0.035225743496003124
        }, 
        "rotateZ": {
          "curve": "CURVE340", 
          "type": "doubleAngle", 
          "value": -9.358184717696018
        }
      }
    }, 
    "NPC_Rig:R_Index_Ctrl_01": {
      "attrs": {
        "rotateX": {
          "curve": "CURVE342", 
          "type": "doubleAngle", 
          "value": 0.0
        }, 
        "rotateY": {
          "curve": "CURVE343", 
          "type": "doubleAngle", 
          "value": 0.0
        }, 
        "rotateZ": {
          "curve": "CURVE344", 
          "type": "doubleAngle", 
          "value": -9.901586302668461
        }
      }
    }, 
    "NPC_Rig:R_Lip_Ctrl_01": {
      "attrs": {
        "translateX": {
          "curve": "CURVE346", 
          "type": "doubleLinear", 
          "value": 0.004975849212834039
        }, 
        "translateY": {
          "curve": "CURVE347", 
          "type": "doubleLinear", 
          "value": 0.014959181308729226
        }, 
        "translateZ": {
          "curve": "CURVE348", 
          "type": "doubleLinear", 
          "value": 0.02884963301558796
        }, 
        "scaleX": {
          "curve": "CURVE349", 
          "type": "double", 
          "value": 1.0
        }, 
        "scaleY": {
          "curve": "CURVE350", 
          "type": "double", 
          "value": 1.0
        }, 
        "visibility": {
          "curve": "CURVE351", 
          "type": "bool", 
          "value": true
        }, 
        "rotateX": {
          "curve": "CURVE352", 
          "type": "doubleAngle", 
          "value": -0.0
        }, 
        "rotateY": {
          "curve": "CURVE353", 
          "type": "doubleAngle", 
          "value": -0.0
        }, 
        "rotateZ": {
          "curve": "CURVE354", 
          "type": "doubleAngle", 
          "value": 0.0
        }, 
        "scaleZ": {
          "curve": "CURVE355", 
          "type": "double", 
          "value": 1.0
        }
      }
    }, 
    "NPC_Rig:Lower_Lip_Ctrl_01": {
      "attrs": {
        "translateX": {
          "curve": "CURVE357", 
          "type": "doubleLinear", 
          "value": 0.0
        }, 
        "translateY": {
          "curve": "CURVE358", 
          "type": "doubleLinear", 
          "value": 0.0
        }, 
        "translateZ": {
          "curve": "CURVE359", 
          "type": "doubleLinear", 
          "value": 0.0
        }, 
        "scaleX": {
          "curve": "CURVE360", 
          "type": "double", 
          "value": 1.0
        }, 
        "scaleY": {
          "curve": "CURVE361", 
          "type": "double", 
          "value": 1.0
        }, 
        "visibility": {
          "curve": "CURVE362", 
          "type": "bool", 
          "value": true
        }, 
        "rotateX": {
          "curve": "CURVE363", 
          "type": "doubleAngle", 
          "value": 0.0
        }, 
        "rotateY": {
          "curve": "CURVE364", 
          "type": "doubleAngle", 
          "value": 0.0
        }, 
        "rotateZ": {
          "curve": "CURVE365", 
          "type": "doubleAngle", 
          "value": 0.0
        }, 
        "scaleZ": {
          "curve": "CURVE366", 
          "type": "double", 
          "value": 1.0
        }
      }
    }, 
    "NPC_Rig:Neck_Ctrl_01": {
      "attrs": {
        "translateX": {
          "curve": "CURVE368", 
          "type": "doubleLinear", 
          "value": -0.0
        }, 
        "translateY": {
          "curve": "CURVE369", 
          "type": "doubleLinear", 
          "value": 0.0
        }, 
        "translateZ": {
          "curve": "CURVE370", 
          "type": "doubleLinear", 
          "value": 0.0
        }, 
        "scaleX": {
          "curve": "CURVE371", 
          "type": "double", 
          "value": 1.0
        }, 
        "scaleY": {
          "curve": "CURVE372", 
          "type": "double", 
          "value": 1.0
        }, 
        "visibility": {
          "curve": "CURVE373", 
          "type": "bool", 
          "value": true
        }, 
        "rotateX": {
          "curve": "CURVE374", 
          "type": "doubleAngle", 
          "value": 4.509078762426344
        }, 
        "rotateY": {
          "curve": "CURVE375", 
          "type": "doubleAngle", 
          "value": -0.0
        }, 
        "rotateZ": {
          "curve": "CURVE376", 
          "type": "doubleAngle", 
          "value": -0.0
        }, 
        "scaleZ": {
          "curve": "CURVE377", 
          "type": "double", 
          "value": 1.0
        }
      }
    }, 
    "NPC_Rig:R_Ear_Ctrl_01": {
      "attrs": {
        "translateX": {
          "curve": "CURVE379", 
          "type": "doubleLinear", 
          "value": 0.0
        }, 
        "translateY": {
          "curve": "CURVE380", 
          "type": "doubleLinear", 
          "value": 0.0
        }, 
        "translateZ": {
          "curve": "CURVE381", 
          "type": "doubleLinear", 
          "value": 0.0
        }, 
        "scaleX": {
          "curve": "CURVE382", 
          "type": "double", 
          "value": 1.0
        }, 
        "scaleY": {
          "curve": "CURVE383", 
          "type": "double", 
          "value": 1.0
        }, 
        "visibility": {
          "curve": "CURVE384", 
          "type": "bool", 
          "value": true
        }, 
        "rotateX": {
          "curve": "CURVE385", 
          "type": "doubleAngle", 
          "value": 0.0
        }, 
        "rotateY": {
          "curve": "CURVE386", 
          "type": "doubleAngle", 
          "value": 0.0
        }, 
        "rotateZ": {
          "curve": "CURVE387", 
          "type": "doubleAngle", 
          "value": 0.0
        }, 
        "scaleZ": {
          "curve": "CURVE388", 
          "type": "double", 
          "value": 1.0
        }
      }
    }, 
    "NPC_Rig:L_Index_Ctrl_03": {
      "attrs": {
        "rotateX": {
          "curve": "CURVE390", 
          "type": "doubleAngle", 
          "value": 0.0
        }, 
        "rotateY": {
          "curve": "CURVE391", 
          "type": "doubleAngle", 
          "value": 0.0
        }, 
        "rotateZ": {
          "curve": "CURVE392", 
          "type": "doubleAngle", 
          "value": 0.0
        }
      }
    }, 
    "NPC_Rig:FK_Tail_Ctrl_01": {
      "attrs": {
        "translateX": {
          "curve": "CURVE394", 
          "type": "doubleLinear", 
          "value": -0.0
        }, 
        "translateY": {
          "curve": "CURVE395", 
          "type": "doubleLinear", 
          "value": 0.0
        }, 
        "translateZ": {
          "curve": "CURVE396", 
          "type": "doubleLinear", 
          "value": 0.0
        }, 
        "scaleX": {
          "curve": "CURVE397", 
          "type": "double", 
          "value": 1.0
        }, 
        "scaleY": {
          "curve": "CURVE398", 
          "type": "double", 
          "value": 1.0
        }, 
        "visibility": {
          "curve": "CURVE399", 
          "type": "bool", 
          "value": true
        }, 
        "rotateX": {
          "curve": "CURVE400", 
          "type": "doubleAngle", 
          "value": 0.0
        }, 
        "rotateY": {
          "curve": "CURVE401", 
          "type": "doubleAngle", 
          "value": -0.0
        }, 
        "rotateZ": {
          "curve": "CURVE402", 
          "type": "doubleAngle", 
          "value": -0.0
        }, 
        "scaleZ": {
          "curve": "CURVE403", 
          "type": "double", 
          "value": 1.0
        }
      }
    }, 
    "NPC_Rig:R_Hand_IKFK": {
      "attrs": {
        "IK_FK_Switch": {
          "curve": "CURVE405", 
          "type": "double", 
          "value": 0.0
        }
      }
    }, 
    "NPC_Rig:L_FK_Clavical_Ctrl_01": {
      "attrs": {
        "rotateX": {
          "curve": "CURVE407", 
          "type": "doubleAngle", 
          "value": 0.0
        }, 
        "rotateY": {
          "curve": "CURVE408", 
          "type": "doubleAngle", 
          "value": 0.0
        }, 
        "rotateZ": {
          "curve": "CURVE409", 
          "type": "doubleAngle", 
          "value": 0.0
        }
      }
    }, 
    "NPC_Rig:L_Ear_Ctrl_01": {
      "attrs": {
        "translateX": {
          "curve": "CURVE411", 
          "type": "doubleLinear", 
          "value": 0.0
        }, 
        "translateY": {
          "curve": "CURVE412", 
          "type": "doubleLinear", 
          "value": 0.0
        }, 
        "translateZ": {
          "curve": "CURVE413", 
          "type": "doubleLinear", 
          "value": 0.0
        }, 
        "scaleX": {
          "curve": "CURVE414", 
          "type": "double", 
          "value": 1.0
        }, 
        "scaleY": {
          "curve": "CURVE415", 
          "type": "double", 
          "value": 1.0
        }, 
        "visibility": {
          "curve": "CURVE416", 
          "type": "bool", 
          "value": true
        }, 
        "rotateX": {
          "curve": "CURVE417", 
          "type": "doubleAngle", 
          "value": 0.0
        }, 
        "rotateY": {
          "curve": "CURVE418", 
          "type": "doubleAngle", 
          "value": 0.0
        }, 
        "rotateZ": {
          "curve": "CURVE419", 
          "type": "doubleAngle", 
          "value": 0.0
        }, 
        "scaleZ": {
          "curve": "CURVE420", 
          "type": "double", 
          "value": 1.0
        }
      }
    }, 
    "NPC_Rig:R_Eye_Ctrl_01": {
      "attrs": {
        "translateX": {
          "curve": "CURVE422", 
          "type": "doubleLinear", 
          "value": 0.0
        }, 
        "translateY": {
          "curve": "CURVE423", 
          "type": "doubleLinear", 
          "value": 0.0
        }, 
        "translateZ": {
          "curve": "CURVE424", 
          "type": "doubleLinear", 
          "value": 0.0
        }, 
        "scaleX": {
          "curve": "CURVE425", 
          "type": "double", 
          "value": 1.0
        }, 
        "scaleY": {
          "curve": "CURVE426", 
          "type": "double", 
          "value": 1.0
        }, 
        "visibility": {
          "curve": "CURVE427", 
          "type": "bool", 
          "value": true
        }, 
        "rotateX": {
          "curve": "CURVE428", 
          "type": "doubleAngle", 
          "value": 0.0
        }, 
        "rotateY": {
          "curve": "CURVE429", 
          "type": "doubleAngle", 
          "value": 0.0
        }, 
        "rotateZ": {
          "curve": "CURVE430", 
          "type": "doubleAngle", 
          "value": 0.0
        }, 
        "scaleZ": {
          "curve": "CURVE431", 
          "type": "double", 
          "value": 1.0
        }
      }
    }, 
    "NPC_Rig:L_FK_Wrist_Ctrl_01": {
      "attrs": {
        "rotateX": {
          "curve": "CURVE433", 
          "type": "doubleAngle", 
          "value": 30.56669781405711
        }, 
        "rotateY": {
          "curve": "CURVE434", 
          "type": "doubleAngle", 
          "value": 0.0
        }, 
        "rotateZ": {
          "curve": "CURVE435", 
          "type": "doubleAngle", 
          "value": 0.0
        }
      }
    }, 
    "NPC_Rig:L_FK_Elbow_Ctrl_01": {
      "attrs": {
        "rotateX": {
          "curve": "CURVE437", 
          "type": "doubleAngle", 
          "value": 0.0
        }, 
        "rotateY": {
          "curve": "CURVE438", 
          "type": "doubleAngle", 
          "value": 0.0
        }, 
        "rotateZ": {
          "curve": "CURVE439", 
          "type": "doubleAngle", 
          "value": 0.0
        }
      }
    }
  }
}