{
  "metadata": {
    "ctime": "1570580483", 
    "version": "1.0.0", 
    "references": [
      {
        "node": "NPC_RigRN", 
        "unresolved": "C:/Users/mercu/Dropbox/maya/projects/SeedQuest/scenes/05_NPC/NPC_Base/NPC_Rig.ma", 
        "namespace": ":NPC_Rig", 
        "filename": "C:/Users/mercu/Dropbox/maya/projects/SeedQuest/scenes/05_NPC/NPC_Base/NPC_Rig.ma"
      }
    ], 
    "user": "mercu", 
    "mayaSceneFile": "C:/Users/mercu/Dropbox/maya/projects/SeedQuest/scenes/Gym/Anim/NPC_Base/gymbros_exercise_wip.0004.ma", 
    "mayaVersion": "2019", 
    "description": ""
  }
,
  "objects": {
    "NPC_Rig:R_Eye_Lower_Ctrl_01": {
      "attrs": {
        "translateX": {
          "type": "doubleLinear", 
          "value": 0.0
        }, 
        "translateY": {
          "type": "doubleLinear", 
          "value": 0.0
        }, 
        "translateZ": {
          "type": "doubleLinear", 
          "value": 0.0
        }, 
        "scaleX": {
          "type": "double", 
          "value": 1.0
        }, 
        "scaleY": {
          "type": "double", 
          "value": 1.0
        }, 
        "visibility": {
          "type": "bool", 
          "value": true
        }, 
        "rotateX": {
          "type": "doubleAngle", 
          "value": 0.0
        }, 
        "rotateY": {
          "type": "doubleAngle", 
          "value": 0.0
        }, 
        "rotateZ": {
          "type": "doubleAngle", 
          "value": 0.0
        }, 
        "scaleZ": {
          "type": "double", 
          "value": 1.0
        }
      }
    }, 
    "NPC_Rig:L_Eyebrow_Inner_Ctrl_01": {
      "attrs": {
        "translateX": {
          "type": "doubleLinear", 
          "value": -0.00017673811851676705
        }, 
        "translateY": {
          "type": "doubleLinear", 
          "value": -0.12784055203765754
        }, 
        "translateZ": {
          "type": "doubleLinear", 
          "value": 0.056269575397387264
        }, 
        "scaleX": {
          "type": "double", 
          "value": 1.0
        }, 
        "scaleY": {
          "type": "double", 
          "value": 1.0
        }, 
        "visibility": {
          "type": "bool", 
          "value": true
        }, 
        "rotateX": {
          "type": "doubleAngle", 
          "value": 0.0
        }, 
        "rotateY": {
          "type": "doubleAngle", 
          "value": 0.0
        }, 
        "rotateZ": {
          "type": "doubleAngle", 
          "value": 0.0
        }, 
        "scaleZ": {
          "type": "double", 
          "value": 1.0
        }
      }
    }, 
    "NPC_Rig:L_Eye_Ctrl_01": {
      "attrs": {
        "translateX": {
          "type": "doubleLinear", 
          "value": 0.0
        }, 
        "translateY": {
          "type": "doubleLinear", 
          "value": 0.0
        }, 
        "translateZ": {
          "type": "doubleLinear", 
          "value": 0.0
        }, 
        "scaleX": {
          "type": "double", 
          "value": 1.0
        }, 
        "scaleY": {
          "type": "double", 
          "value": 1.0
        }, 
        "visibility": {
          "type": "bool", 
          "value": true
        }, 
        "rotateX": {
          "type": "doubleAngle", 
          "value": 103.7689946637504
        }, 
        "rotateY": {
          "type": "doubleAngle", 
          "value": 0.0
        }, 
        "rotateZ": {
          "type": "doubleAngle", 
          "value": 0.0
        }, 
        "scaleZ": {
          "type": "double", 
          "value": 1.0
        }
      }
    }, 
    "NPC_Rig:R_Eyebrow_Inner_Ctrl_01": {
      "attrs": {
        "translateX": {
          "type": "doubleLinear", 
          "value": 0.00017673811851676705
        }, 
        "translateY": {
          "type": "doubleLinear", 
          "value": -0.12784055203765754
        }, 
        "translateZ": {
          "type": "doubleLinear", 
          "value": 0.056269575397387264
        }, 
        "scaleX": {
          "type": "double", 
          "value": 1.0
        }, 
        "scaleY": {
          "type": "double", 
          "value": 1.0
        }, 
        "visibility": {
          "type": "bool", 
          "value": true
        }, 
        "rotateX": {
          "type": "doubleAngle", 
          "value": 0.0
        }, 
        "rotateY": {
          "type": "doubleAngle", 
          "value": 0.0
        }, 
        "rotateZ": {
          "type": "doubleAngle", 
          "value": 0.0
        }, 
        "scaleZ": {
          "type": "double", 
          "value": 1.0
        }
      }
    }, 
    "NPC_Rig:L_Eyebrow_Outer_Ctrl_01": {
      "attrs": {
        "translateX": {
          "type": "doubleLinear", 
          "value": -0.003945243955383225
        }, 
        "translateY": {
          "type": "doubleLinear", 
          "value": -0.06458710588285033
        }, 
        "translateZ": {
          "type": "doubleLinear", 
          "value": -0.010934695694917297
        }, 
        "scaleX": {
          "type": "double", 
          "value": 1.0
        }, 
        "scaleY": {
          "type": "double", 
          "value": 1.0
        }, 
        "visibility": {
          "type": "bool", 
          "value": true
        }, 
        "rotateX": {
          "type": "doubleAngle", 
          "value": 21.24326308275786
        }, 
        "rotateY": {
          "type": "doubleAngle", 
          "value": 0.0
        }, 
        "rotateZ": {
          "type": "doubleAngle", 
          "value": 0.0
        }, 
        "scaleZ": {
          "type": "double", 
          "value": 1.0
        }
      }
    }, 
    "NPC_Rig:R_Eye_Ctrl_01": {
      "attrs": {
        "translateX": {
          "type": "doubleLinear", 
          "value": 0.0
        }, 
        "translateY": {
          "type": "doubleLinear", 
          "value": 0.0
        }, 
        "translateZ": {
          "type": "doubleLinear", 
          "value": 0.0
        }, 
        "scaleX": {
          "type": "double", 
          "value": 1.0
        }, 
        "scaleY": {
          "type": "double", 
          "value": 1.0
        }, 
        "visibility": {
          "type": "bool", 
          "value": true
        }, 
        "rotateX": {
          "type": "doubleAngle", 
          "value": 103.7689946637504
        }, 
        "rotateY": {
          "type": "doubleAngle", 
          "value": 0.0
        }, 
        "rotateZ": {
          "type": "doubleAngle", 
          "value": 0.0
        }, 
        "scaleZ": {
          "type": "double", 
          "value": 1.0
        }
      }
    }, 
    "NPC_Rig:R_Eye_Upper_Ctrl_01": {
      "attrs": {
        "translateX": {
          "type": "doubleLinear", 
          "value": 0.0
        }, 
        "translateY": {
          "type": "doubleLinear", 
          "value": 0.0
        }, 
        "translateZ": {
          "type": "doubleLinear", 
          "value": 0.0
        }, 
        "scaleX": {
          "type": "double", 
          "value": 1.0
        }, 
        "scaleY": {
          "type": "double", 
          "value": 1.0
        }, 
        "visibility": {
          "type": "bool", 
          "value": true
        }, 
        "rotateX": {
          "type": "doubleAngle", 
          "value": 0.0
        }, 
        "rotateY": {
          "type": "doubleAngle", 
          "value": 0.0
        }, 
        "rotateZ": {
          "type": "doubleAngle", 
          "value": 0.0
        }, 
        "scaleZ": {
          "type": "double", 
          "value": 1.0
        }
      }
    }, 
    "NPC_Rig:L_Eye_Lower_Ctrl_01": {
      "attrs": {
        "translateX": {
          "type": "doubleLinear", 
          "value": 0.0
        }, 
        "translateY": {
          "type": "doubleLinear", 
          "value": 0.0
        }, 
        "translateZ": {
          "type": "doubleLinear", 
          "value": 0.0
        }, 
        "scaleX": {
          "type": "double", 
          "value": 1.0
        }, 
        "scaleY": {
          "type": "double", 
          "value": 1.0
        }, 
        "visibility": {
          "type": "bool", 
          "value": true
        }, 
        "rotateX": {
          "type": "doubleAngle", 
          "value": 0.0
        }, 
        "rotateY": {
          "type": "doubleAngle", 
          "value": 0.0
        }, 
        "rotateZ": {
          "type": "doubleAngle", 
          "value": 0.0
        }, 
        "scaleZ": {
          "type": "double", 
          "value": 1.0
        }
      }
    }, 
    "NPC_Rig:L_Eye_Upper_Ctrl_01": {
      "attrs": {
        "translateX": {
          "type": "doubleLinear", 
          "value": 0.0
        }, 
        "translateY": {
          "type": "doubleLinear", 
          "value": 0.0
        }, 
        "translateZ": {
          "type": "doubleLinear", 
          "value": 0.0
        }, 
        "scaleX": {
          "type": "double", 
          "value": 1.0
        }, 
        "scaleY": {
          "type": "double", 
          "value": 1.0
        }, 
        "visibility": {
          "type": "bool", 
          "value": true
        }, 
        "rotateX": {
          "type": "doubleAngle", 
          "value": 0.0
        }, 
        "rotateY": {
          "type": "doubleAngle", 
          "value": 0.0
        }, 
        "rotateZ": {
          "type": "doubleAngle", 
          "value": 0.0
        }, 
        "scaleZ": {
          "type": "double", 
          "value": 1.0
        }
      }
    }, 
    "NPC_Rig:R_Eyebrow_Outer_Ctrl_01": {
      "attrs": {
        "translateX": {
          "type": "doubleLinear", 
          "value": 0.003945243955383225
        }, 
        "translateY": {
          "type": "doubleLinear", 
          "value": -0.06458710588285033
        }, 
        "translateZ": {
          "type": "doubleLinear", 
          "value": -0.010934695694917297
        }, 
        "scaleX": {
          "type": "double", 
          "value": 1.0
        }, 
        "scaleY": {
          "type": "double", 
          "value": 1.0
        }, 
        "visibility": {
          "type": "bool", 
          "value": true
        }, 
        "rotateX": {
          "type": "doubleAngle", 
          "value": 21.24326308275786
        }, 
        "rotateY": {
          "type": "doubleAngle", 
          "value": 0.0
        }, 
        "rotateZ": {
          "type": "doubleAngle", 
          "value": 0.0
        }, 
        "scaleZ": {
          "type": "double", 
          "value": 1.0
        }
      }
    }
  }
}